experiences/__init__.py
experiences/utils.py
experiences/length/__init__.py
experiences/length/api.py
experiences/length/core.py
experiences-0.1.3.dist-info/LICENSE
experiences-0.1.3.dist-info/METADATA
experiences-0.1.3.dist-info/WHEEL
experiences-0.1.3.dist-info/top_level.txt
experiences-0.1.3.dist-info/RECORD
